{
  "id": "4b6db602-866e-4a5d-8439-5ff6ed4148eb",
  "ticker": "AMZN",
  "status": "OPEN",
  "transactions": [
    {
      "id": "8dcadb6d-4edb-49fc-999b-bddf538b3542",
      "timestamp": "2025-07-22T00:00:00",
      "type": "ENTRY",
      "quantity": 10.0,
      "price": 927.3541888071726,
      "commission": 1.0,
      "slippage": 0.0,
      "order_id": null
    }
  ],
  "order_history": [
    {
      "timestamp": "2025-07-22T00:00:00",
      "order_id": "oid_AMZN_43",
      "action": "BUY",
      "status": "FILLED",
      "message": "Initial Entry",
      "quantity": 10.0,
      "type": "MKT",
      "limit_price": null,
      "stop_price": null,
      "trigger_price": null,
      "note": "Generated Entry",
      "details": {}
    },
    {
      "timestamp": "2025-07-22T00:00:00",
      "order_id": "oid_AMZN_43_stop",
      "action": "SELL",
      "status": "SUBMITTED",
      "message": "Initial Stop",
      "quantity": -10.0,
      "type": "STP",
      "limit_price": null,
      "stop_price": 880.9864793668139,
      "trigger_price": null,
      "note": "Protection",
      "details": {}
    }
  ],
  "active_orders": {
    "oid_AMZN_43_stop": "STOP"
  },
  "initial_stop_price": 880.9864793668139,
  "current_stop_price": 880.9864793668139,
  "entry_date": "2025-07-22T00:00:00",
  "notes": ""
}