{
  "id": "97f3cb7d-5af6-4928-8527-efd87726a5e1",
  "ticker": "WYFI",
  "status": "CLOSED",
  "trade_type": "STOCK",
  "transactions": [
    {
      "id": "759cbbf2",
      "timestamp": "2025-09-10T12:50:53",
      "type": "ENTRY",
      "quantity": 8.0,
      "price": 23.35,
      "commission": 2.0,
      "slippage": 0.0,
      "order_id": null
    },
    {
      "id": "e6ad16f6",
      "timestamp": "2025-09-15T10:08:44",
      "type": "ENTRY",
      "quantity": 8.0,
      "price": 20.86,
      "commission": 2.0,
      "slippage": 0.0,
      "order_id": null
    },
    {
      "id": "0aa6de0a",
      "timestamp": "2025-09-24T15:29:21",
      "type": "EXIT",
      "quantity": -8.0,
      "price": 25.8,
      "commission": 2.0,
      "slippage": 0.0,
      "order_id": null
    },
    {
      "id": "34a793c3",
      "timestamp": "2025-10-14T09:43:49",
      "type": "EXIT",
      "quantity": -8.0,
      "price": 35.03,
      "commission": 2.0,
      "slippage": 0.0,
      "order_id": null
    }
  ],
  "order_history": [],
  "active_orders": {},
  "initial_stop_price": 0,
  "current_stop_price": null,
  "entry_date": "2025-09-10T12:50:53",
  "notes": "legacy | WHITEFIBER INC | ISIN:KYG961151035",
  "currency": "USD",
  "exchange": ""
}